xsdata_rootfinder/__init__.py
xsdata_rootfinder/py.typed
xsdata_rootfinder-0.1.0.dist-info/LICENSE
xsdata_rootfinder-0.1.0.dist-info/METADATA
xsdata_rootfinder-0.1.0.dist-info/WHEEL
xsdata_rootfinder-0.1.0.dist-info/RECORD
