Metadata-Version: 2.3
Name: xsdata-rootfinder
Version: 0.1.0
Summary: A lightweight Python package to identify the top-level dataclass in files generated by xsdata, representing the root schema element.
License: MIT
Keywords: xsdata,root,schema,top-level
Author: galactixx
Requires-Python: >=3.9
Classifier: License :: OSI Approved :: MIT License
Classifier: Programming Language :: Python :: 3
Classifier: Programming Language :: Python :: 3.9
Classifier: Programming Language :: Python :: 3.10
Classifier: Programming Language :: Python :: 3.11
Classifier: Programming Language :: Python :: 3.12
Classifier: Programming Language :: Python :: 3.13
Requires-Dist: libcst (>=1.00)
Requires-Dist: pathvalidate (>=3.2.0)
Requires-Dist: typing_extensions (>=4.6.0)
Project-URL: Homepage, https://github.com/galactixx/xsdata-rootfinder
Project-URL: Repository, https://github.com/galactixx/xsdata-rootfinder
